cirun/__about__.py
cirun/__init__.py
cirun/client.py
cirun/cloud.py
cirun/main.py
cirun/repo.py
cirun/utils.py
cirun/tests/__init__.py
cirun/tests/test_client.py
cirun/tests/test_integration.py
cirun-0.30.dist-info/METADATA
cirun-0.30.dist-info/WHEEL
cirun-0.30.dist-info/entry_points.txt
cirun-0.30.dist-info/licenses/LICENSE.txt
cirun-0.30.dist-info/RECORD
