Metadata-Version: 2.1
Name: cirun
Version: 0.30
Summary: Cirun Python Client
Project-URL: Documentation, https://github.com/aktechlabs/cirun-py#readme
Project-URL: Issues, https://github.com/aktechlabs/cirun-py/issues
Project-URL: Source, https://github.com/aktechlabs/cirun-py
Author-email: Amit Kumar <amit@cirun.io>
License-Expression: MIT
License-File: LICENSE.txt
Classifier: Development Status :: 4 - Beta
Classifier: Programming Language :: Python
Classifier: Programming Language :: Python :: 3.8
Classifier: Programming Language :: Python :: 3.9
Classifier: Programming Language :: Python :: 3.10
Classifier: Programming Language :: Python :: 3.11
Classifier: Programming Language :: Python :: Implementation :: CPython
Classifier: Programming Language :: Python :: Implementation :: PyPy
Requires-Python: >=3.7
Requires-Dist: hatch
Requires-Dist: hatchling
Requires-Dist: requests
Requires-Dist: rich
Requires-Dist: typer
